<?xml version="1.0" encoding="UTF-8"?>
<!DOCTYPE mapper PUBLIC "-//mybatis.org//DTD Mapper 3.0//EN" "http://mybatis.org/dtd/mybatis-3-mapper.dtd">
<mapper namespace="cn.dandong.mapper.EthnicMapper">
  <resultMap id="BaseResultMap" type="cn.dandong.entity.Ethnic">
    <!--
      WARNING - @mbg.generated
      This element is automatically generated by MyBatis Generator, do not modify.
      This element was generated on Sun Aug 11 13:16:36 CST 2019.
    -->
    <id column="eid" jdbcType="INTEGER" property="eid" />
    <result column="ename" jdbcType="VARCHAR" property="ename" />
    <result column="remarks" jdbcType="VARCHAR" property="remarks" />
  </resultMap>
  <delete id="deleteByPrimaryKey" parameterType="java.lang.Integer">
    <!--
      WARNING - @mbg.generated
      This element is automatically generated by MyBatis Generator, do not modify.
      This element was generated on Sun Aug 11 13:16:36 CST 2019.
    -->
    delete from ethnic
    where eid = #{eid,jdbcType=INTEGER}
  </delete>
  <insert id="insert" parameterType="cn.dandong.entity.Ethnic">
    <!--
      WARNING - @mbg.generated
      This element is automatically generated by MyBatis Generator, do not modify.
      This element was generated on Sun Aug 11 13:16:36 CST 2019.
    -->
    insert into ethnic (eid, ename, remarks
      )
    values (#{eid,jdbcType=INTEGER}, #{ename,jdbcType=VARCHAR}, #{remarks,jdbcType=VARCHAR}
      )
  </insert>
  <update id="updateByPrimaryKey" parameterType="cn.dandong.entity.Ethnic">
    <!--
      WARNING - @mbg.generated
      This element is automatically generated by MyBatis Generator, do not modify.
      This element was generated on Sun Aug 11 13:16:36 CST 2019.
    -->
    update ethnic
    set ename = #{ename,jdbcType=VARCHAR},
      remarks = #{remarks,jdbcType=VARCHAR}
    where eid = #{eid,jdbcType=INTEGER}
  </update>
  <select id="selectByPrimaryKey" parameterType="java.lang.Integer" resultMap="BaseResultMap">
    <!--
      WARNING - @mbg.generated
      This element is automatically generated by MyBatis Generator, do not modify.
      This element was generated on Sun Aug 11 13:16:36 CST 2019.
    -->
    select eid, ename, remarks
    from ethnic
    where eid = #{eid,jdbcType=INTEGER}
  </select>
  <select id="selectAll" resultMap="BaseResultMap">
    <!--
      WARNING - @mbg.generated
      This element is automatically generated by MyBatis Generator, do not modify.
      This element was generated on Sun Aug 11 13:16:36 CST 2019.
    -->
    select eid, ename, remarks
    from ethnic
  </select>
</mapper>